platon_typing/__init__.py
platon_typing/abi.py
platon_typing/bls.py
platon_typing/discovery.py
platon_typing/encoding.py
platon_typing/enums.py
platon_typing/ethpm.py
platon_typing/evm.py
platon_typing/py.typed
platon_typing-1.2.0.dist-info/LICENSE
platon_typing-1.2.0.dist-info/METADATA
platon_typing-1.2.0.dist-info/WHEEL
platon_typing-1.2.0.dist-info/top_level.txt
platon_typing-1.2.0.dist-info/RECORD
